{"success":true,"error":null,"response":[{"id":"DAFH","loc":{"long":3.3166666666667,"lat":32.933333333333},"place":{"name":"tilrempt\/hassi","state":"","country":"dz"},"profile":{"tz":"Africa\/Algiers","elevM":774,"elevFT":2539},"obTimestamp":1416571200,"obDateTime":"2014-11-21T13:00:00+01:00","ob":{"timestamp":1416571200,"dateTimeISO":"2014-11-21T13:00:00+01:00","tempC":25,"tempF":77,"dewpointC":6,"dewpointF":43,"humidity":30,"pressureMB":1024,"pressureIN":30.24,"spressureMB":938,"spressureIN":27.7,"altimeterMB":null,"altimeterIN":null,"windKTS":null,"windKPH":null,"windMPH":null,"windSpeedKTS":null,"windSpeedKPH":null,"windSpeedMPH":null,"windDirDEG":0,"windDir":"N","windGustKTS":null,"windGustKPH":null,"windGustMPH":null,"flightRule":"LIFR","visibilityKM":11.265408,"visibilityMI":7,"weather":"Mostly Sunny","weatherShort":"Mostly Sunny","weatherCoded":"::FW","weatherPrimary":"Mostly Sunny","weatherPrimaryCoded":"::FW","cloudsCoded":"FW","icon":"pcloudy.png","heatindexC":25,"heatindexF":77,"windchillC":25,"windchillF":77,"feelslikeC":25,"feelslikeF":77,"isDay":true,"sunrise":1416550977,"sunriseISO":"2014-11-21T07:22:57+01:00","sunset":1416588146,"sunsetISO":"2014-11-21T17:42:26+01:00","snowDepthCM":null,"snowDepthIN":null,"precipMM":null,"precipIN":null,"solradWM2":null,"sky":19,"light":79},"raw":"DAFH 211200Z \/\/\/\/\/KT CAVOK 25\/06 Q1024"},{"id":"DATM","loc":{"long":0.91666666666667,"lat":21.383333333333},"place":{"name":"bordj mokhtar","state":"","country":"dz"},"profile":{"tz":"Africa\/Algiers","elevM":396,"elevFT":1299},"obTimestamp":1416571200,"obDateTime":"2014-11-21T13:00:00+01:00","ob":{"timestamp":1416571200,"dateTimeISO":"2014-11-21T13:00:00+01:00","tempC":33,"tempF":91,"dewpointC":6,"dewpointF":43,"humidity":18,"pressureMB":1016,"pressureIN":30,"spressureMB":972,"spressureIN":28.7,"altimeterMB":null,"altimeterIN":null,"windKTS":28,"windKPH":52,"windMPH":32,"windSpeedKTS":28,"windSpeedKPH":52,"windSpeedMPH":32,"windDirDEG":180,"windDir":"S","windGustKTS":null,"windGustKPH":null,"windGustMPH":null,"flightRule":"LIFR","visibilityKM":1.5,"visibilityMI":0.93,"weather":"Partly Cloudy with Blowing Sand","weatherShort":"Blowing Sand","weatherCoded":"::BN,::SC","weatherPrimary":"Blowing Sand","weatherPrimaryCoded":"::BN","cloudsCoded":"SC","icon":"hazy.png","heatindexC":33,"heatindexF":91,"windchillC":33,"windchillF":91,"feelslikeC":33,"feelslikeF":91,"isDay":true,"sunrise":1416550274,"sunriseISO":"2014-11-21T07:11:14+01:00","sunset":1416590002,"sunsetISO":"2014-11-21T18:13:22+01:00","snowDepthCM":null,"snowDepthIN":null,"precipMM":null,"precipIN":null,"solradWM2":null,"light":69,"sky":44},"raw":"DATM 211200Z 18028KT 1500 DRSA SCT046TCU SCT100 33\/06 Q1016"},{"id":"DAAY","loc":{"long":-0.25,"lat":33.533333333333},"place":{"name":"mecheria","state":"","country":"dz"},"profile":{"tz":"Africa\/Algiers","elevM":1149,"elevFT":3770},"obTimestamp":1416574800,"obDateTime":"2014-11-21T14:00:00+01:00","ob":{"timestamp":1416574800,"dateTimeISO":"2014-11-21T14:00:00+01:00","tempC":22,"tempF":72,"dewpointC":5,"dewpointF":41,"humidity":33,"pressureMB":1023,"pressureIN":30.21,"spressureMB":897,"spressureIN":26.49,"altimeterMB":null,"altimeterIN":null,"windKTS":22,"windKPH":41,"windMPH":25,"windSpeedKTS":22,"windSpeedKPH":41,"windSpeedMPH":25,"windDirDEG":140,"windDir":"SE","windGustKTS":null,"windGustKPH":null,"windGustMPH":null,"flightRule":"LIFR","visibilityKM":4,"visibilityMI":2.49,"weather":"Partly Cloudy with Blowing Sand","weatherShort":"Blowing Sand","weatherCoded":"::BN,::SC","weatherPrimary":"Blowing Sand","weatherPrimaryCoded":"::BN","cloudsCoded":"SC","icon":"hazy.png","heatindexC":22,"heatindexF":72,"windchillC":22,"windchillF":72,"feelslikeC":22,"feelslikeF":72,"isDay":true,"sunrise":1416551909,"sunriseISO":"2014-11-21T07:38:29+01:00","sunset":1416588926,"sunsetISO":"2014-11-21T17:55:26+01:00","snowDepthCM":null,"snowDepthIN":null,"precipMM":null,"precipIN":null,"solradWM2":null,"light":64,"sky":44},"raw":"DAAY 211300Z 14022KT 4000 DRSA SCT030 SCT100 22\/05 Q1023"},{"id":"DAUL","loc":{"long":2.9166666666667,"lat":33.766666666667},"place":{"name":"laghouat","state":"","country":"dz"},"profile":{"tz":"Africa\/Algiers","elevM":765,"elevFT":2510},"obTimestamp":1416574800,"obDateTime":"2014-11-21T14:00:00+01:00","ob":{"timestamp":1416574800,"dateTimeISO":"2014-11-21T14:00:00+01:00","tempC":24,"tempF":75,"dewpointC":5,"dewpointF":41,"humidity":29,"pressureMB":1023,"pressureIN":30.21,"spressureMB":938,"spressureIN":27.7,"altimeterMB":null,"altimeterIN":null,"windKTS":8,"windKPH":15,"windMPH":9,"windSpeedKTS":8,"windSpeedKPH":15,"windSpeedMPH":9,"windDirDEG":200,"windDir":"SSW","windGustKTS":null,"windGustKPH":null,"windGustMPH":null,"flightRule":"LIFR","visibilityKM":null,"visibilityMI":null,"weather":"Partly Cloudy","weatherShort":"Partly Cloudy","weatherCoded":"::SC","weatherPrimary":"Partly Cloudy","weatherPrimaryCoded":"::SC","cloudsCoded":"SC","icon":"pcloudy.png","heatindexC":24,"heatindexF":75,"windchillC":24,"windchillF":75,"feelslikeC":24,"feelslikeF":75,"isDay":true,"sunrise":1416551178,"sunriseISO":"2014-11-21T07:26:18+01:00","sunset":1416588137,"sunsetISO":"2014-11-21T17:42:17+01:00","snowDepthCM":null,"snowDepthIN":null,"precipMM":null,"precipIN":null,"solradWM2":null,"light":64,"sky":44},"raw":"DAUL 211300Z 20008KT 9999 FEW033 SCT200 24\/05 Q1023"},{"id":"DAOR","loc":{"long":-2.2666666666667,"lat":31.65},"place":{"name":"bechar\/ouakda","state":"","country":"dz"},"profile":{"tz":"Africa\/Algiers","elevM":773,"elevFT":2536},"obTimestamp":1416574800,"obDateTime":"2014-11-21T14:00:00+01:00","ob":{"timestamp":1416574800,"dateTimeISO":"2014-11-21T14:00:00+01:00","tempC":24,"tempF":75,"dewpointC":2,"dewpointF":36,"humidity":24,"pressureMB":1020,"pressureIN":30.12,"spressureMB":934,"spressureIN":27.58,"altimeterMB":null,"altimeterIN":null,"windKTS":0,"windKPH":0,"windMPH":0,"windSpeedKTS":0,"windSpeedKPH":0,"windSpeedMPH":0,"windDirDEG":0,"windDir":"N","windGustKTS":null,"windGustKPH":null,"windGustMPH":null,"flightRule":"LIFR","visibilityKM":null,"visibilityMI":null,"weather":"Partly Cloudy","weatherShort":"Partly Cloudy","weatherCoded":"::SC","weatherPrimary":"Partly Cloudy","weatherPrimaryCoded":"::SC","cloudsCoded":"SC","icon":"pcloudy.png","heatindexC":24,"heatindexF":75,"windchillC":24,"windchillF":75,"feelslikeC":24,"feelslikeF":75,"isDay":true,"sunrise":1416552161,"sunriseISO":"2014-11-21T07:42:41+01:00","sunset":1416589643,"sunsetISO":"2014-11-21T18:07:23+01:00","snowDepthCM":null,"snowDepthIN":null,"precipMM":null,"precipIN":null,"solradWM2":null,"light":65,"sky":44},"raw":"DAOR 211300Z 00000KT 9999 FEW033 SCT100 24\/02 Q1020"},{"id":"DAAV","loc":{"long":5.8833333333333,"lat":36.8},"place":{"name":"jijel\/taher","state":"","country":"dz"},"profile":{"tz":"Africa\/Algiers","elevM":11,"elevFT":36},"obTimestamp":1416574800,"obDateTime":"2014-11-21T14:00:00+01:00","ob":{"timestamp":1416574800,"dateTimeISO":"2014-11-21T14:00:00+01:00","tempC":26,"tempF":79,"dewpointC":11,"dewpointF":52,"humidity":39,"pressureMB":1018,"pressureIN":30.06,"spressureMB":1017,"spressureIN":30.03,"altimeterMB":null,"altimeterIN":null,"windKTS":6,"windKPH":11,"windMPH":7,"windSpeedKTS":6,"windSpeedKPH":11,"windSpeedMPH":7,"windDirDEG":320,"windDir":"NW","windGustKTS":null,"windGustKPH":null,"windGustMPH":null,"flightRule":"LIFR","visibilityKM":11.265408,"visibilityMI":7,"weather":"Mostly Sunny","weatherShort":"Mostly Sunny","weatherCoded":"::FW","weatherPrimary":"Mostly Sunny","weatherPrimaryCoded":"::FW","cloudsCoded":"FW","icon":"pcloudy.png","heatindexC":26,"heatindexF":79,"windchillC":26,"windchillF":79,"feelslikeC":26,"feelslikeF":79,"isDay":true,"sunrise":1416550866,"sunriseISO":"2014-11-21T07:21:06+01:00","sunset":1416587025,"sunsetISO":"2014-11-21T17:23:45+01:00","snowDepthCM":null,"snowDepthIN":null,"precipMM":null,"precipIN":null,"solradWM2":null,"sky":19,"light":68},"raw":"DAAV 211300Z 32006KT CAVOK 26\/11 Q1018"},{"id":"DAUB","loc":{"long":5.7166666666667,"lat":34.783333333333},"place":{"name":"biskra","state":"","country":"dz"},"profile":{"tz":"Africa\/Algiers","elevM":87,"elevFT":285},"obTimestamp":1416574800,"obDateTime":"2014-11-21T14:00:00+01:00","ob":{"timestamp":1416574800,"dateTimeISO":"2014-11-21T14:00:00+01:00","tempC":27,"tempF":81,"dewpointC":7,"dewpointF":45,"humidity":28,"pressureMB":1021,"pressureIN":30.15,"spressureMB":1011,"spressureIN":29.85,"altimeterMB":null,"altimeterIN":null,"windKTS":null,"windKPH":null,"windMPH":null,"windSpeedKTS":null,"windSpeedKPH":null,"windSpeedMPH":null,"windDirDEG":0,"windDir":"N","windGustKTS":null,"windGustKPH":null,"windGustMPH":null,"flightRule":"LIFR","visibilityKM":11.265408,"visibilityMI":7,"weather":"Mostly Sunny","weatherShort":"Mostly Sunny","weatherCoded":"::FW","weatherPrimary":"Mostly Sunny","weatherPrimaryCoded":"::FW","cloudsCoded":"FW","icon":"pcloudy.png","heatindexC":27,"heatindexF":81,"windchillC":27,"windchillF":81,"feelslikeC":27,"feelslikeF":81,"isDay":true,"sunrise":1416550636,"sunriseISO":"2014-11-21T07:17:16+01:00","sunset":1416587335,"sunsetISO":"2014-11-21T17:28:55+01:00","snowDepthCM":null,"snowDepthIN":null,"precipMM":null,"precipIN":null,"solradWM2":null,"sky":19,"light":68},"raw":"DAUB 211300Z \/\/\/\/\/KT CAVOK 27\/07 Q1021"},{"id":"DAAP","loc":{"long":8.6166666666667,"lat":26.716666666667},"place":{"name":"illizi\/illirane","state":"","country":"dz"},"profile":{"tz":"Africa\/Algiers","elevM":558,"elevFT":1831},"obTimestamp":1416574800,"obDateTime":"2014-11-21T14:00:00+01:00","ob":{"timestamp":1416574800,"dateTimeISO":"2014-11-21T14:00:00+01:00","tempC":28,"tempF":82,"dewpointC":3,"dewpointF":37,"humidity":20,"pressureMB":1021,"pressureIN":30.15,"spressureMB":959,"spressureIN":28.32,"altimeterMB":null,"altimeterIN":null,"windKTS":0,"windKPH":0,"windMPH":0,"windSpeedKTS":0,"windSpeedKPH":0,"windSpeedMPH":0,"windDirDEG":0,"windDir":"N","windGustKTS":null,"windGustKPH":null,"windGustMPH":null,"flightRule":"LIFR","visibilityKM":11.265408,"visibilityMI":7,"weather":"Mostly Sunny","weatherShort":"Mostly Sunny","weatherCoded":"::FW","weatherPrimary":"Mostly Sunny","weatherPrimaryCoded":"::FW","cloudsCoded":"FW","icon":"pcloudy.png","heatindexC":28,"heatindexF":82,"windchillC":28,"windchillF":82,"feelslikeC":28,"feelslikeF":82,"isDay":true,"sunrise":1416548982,"sunriseISO":"2014-11-21T06:49:42+01:00","sunset":1416587597,"sunsetISO":"2014-11-21T17:33:17+01:00","snowDepthCM":null,"snowDepthIN":null,"precipMM":null,"precipIN":null,"solradWM2":null,"sky":19,"light":68},"raw":"DAAP 211300Z 00000KT CAVOK 28\/03 Q1021"},{"id":"DAAS","loc":{"long":5.3333333333333,"lat":36.183333333333},"place":{"name":"setif\/ain-arnat","state":"","country":"dz"},"profile":{"tz":"Africa\/Algiers","elevM":1038,"elevFT":3406},"obTimestamp":1416574800,"obDateTime":"2014-11-21T14:00:00+01:00","ob":{"timestamp":1416574800,"dateTimeISO":"2014-11-21T14:00:00+01:00","tempC":22,"tempF":72,"dewpointC":5,"dewpointF":41,"humidity":33,"pressureMB":1024,"pressureIN":30.24,"spressureMB":909,"spressureIN":26.84,"altimeterMB":null,"altimeterIN":null,"windKTS":8,"windKPH":15,"windMPH":9,"windSpeedKTS":8,"windSpeedKPH":15,"windSpeedMPH":9,"windDirDEG":260,"windDir":"W","windGustKTS":null,"windGustKPH":null,"windGustMPH":null,"flightRule":"LIFR","visibilityKM":11.265408,"visibilityMI":7,"weather":"Mostly Sunny","weatherShort":"Mostly Sunny","weatherCoded":"::FW","weatherPrimary":"Mostly Sunny","weatherPrimaryCoded":"::FW","cloudsCoded":"FW","icon":"pcloudy.png","heatindexC":22,"heatindexF":72,"windchillC":22,"windchillF":72,"feelslikeC":22,"feelslikeF":72,"isDay":true,"sunrise":1416550914,"sunriseISO":"2014-11-21T07:21:54+01:00","sunset":1416587241,"sunsetISO":"2014-11-21T17:27:21+01:00","snowDepthCM":null,"snowDepthIN":null,"precipMM":null,"precipIN":null,"solradWM2":null,"sky":19,"light":68},"raw":"DAAS 211300Z 26008KT CAVOK 22\/05 Q1024"},{"id":"DAAE","loc":{"long":5.0666666666667,"lat":36.716666666667},"place":{"name":"bejaia\/soummam","state":"","country":"dz"},"profile":{"tz":"Africa\/Algiers","elevM":2,"elevFT":7},"obTimestamp":1416574800,"obDateTime":"2014-11-21T14:00:00+01:00","ob":{"timestamp":1416574800,"dateTimeISO":"2014-11-21T14:00:00+01:00","tempC":30,"tempF":86,"dewpointC":13,"dewpointF":55,"humidity":35,"pressureMB":1018,"pressureIN":30.06,"spressureMB":1018,"spressureIN":30.06,"altimeterMB":null,"altimeterIN":null,"windKTS":12,"windKPH":22,"windMPH":14,"windSpeedKTS":12,"windSpeedKPH":22,"windSpeedMPH":14,"windDirDEG":280,"windDir":"W","windGustKTS":null,"windGustKPH":null,"windGustMPH":null,"flightRule":"LIFR","visibilityKM":11.265408,"visibilityMI":7,"weather":"Mostly Sunny","weatherShort":"Mostly Sunny","weatherCoded":"::FW","weatherPrimary":"Mostly Sunny","weatherPrimaryCoded":"::FW","cloudsCoded":"FW","icon":"pcloudy.png","heatindexC":30,"heatindexF":86,"windchillC":30,"windchillF":86,"feelslikeC":30,"feelslikeF":86,"isDay":true,"sunrise":1416551051,"sunriseISO":"2014-11-21T07:24:11+01:00","sunset":1416587232,"sunsetISO":"2014-11-21T17:27:12+01:00","snowDepthCM":null,"snowDepthIN":null,"precipMM":null,"precipIN":null,"solradWM2":null,"sky":19,"light":69},"raw":"DAAE 211300Z 28012KT CAVOK 30\/13 Q1018"},{"id":"DAOV","loc":{"long":0.15,"lat":35.2},"place":{"name":"mascara\/ghriss","state":"","country":"dz"},"profile":{"tz":"Africa\/Algiers","elevM":514,"elevFT":1686},"obTimestamp":1416574800,"obDateTime":"2014-11-21T14:00:00+01:00","ob":{"timestamp":1416574800,"dateTimeISO":"2014-11-21T14:00:00+01:00","tempC":25,"tempF":77,"dewpointC":3,"dewpointF":37,"humidity":24,"pressureMB":1018,"pressureIN":30.06,"spressureMB":960,"spressureIN":28.35,"altimeterMB":null,"altimeterIN":null,"windKTS":18,"windKPH":33,"windMPH":21,"windSpeedKTS":18,"windSpeedKPH":33,"windSpeedMPH":21,"windDirDEG":170,"windDir":"S","windGustKTS":null,"windGustKPH":null,"windGustMPH":null,"flightRule":"LIFR","visibilityKM":11.265408,"visibilityMI":7,"weather":"Mostly Sunny","weatherShort":"Mostly Sunny","weatherCoded":"::FW","weatherPrimary":"Mostly Sunny","weatherPrimaryCoded":"::FW","cloudsCoded":"FW","icon":"pcloudy.png","heatindexC":25,"heatindexF":77,"windchillC":25,"windchillF":77,"feelslikeC":25,"feelslikeF":77,"isDay":true,"sunrise":1416552028,"sunriseISO":"2014-11-21T07:40:28+01:00","sunset":1416588616,"sunsetISO":"2014-11-21T17:50:16+01:00","snowDepthCM":null,"snowDepthIN":null,"precipMM":null,"precipIN":null,"solradWM2":null,"sky":19,"light":75},"raw":"DAOV 211300Z 17018KT CAVOK 25\/03 Q1018"},{"id":"DAUG","loc":{"long":3.8166666666667,"lat":32.366666666667},"place":{"name":"ghardaia\/noumera","state":"","country":"dz"},"profile":{"tz":"Africa\/Algiers","elevM":450,"elevFT":1476},"obTimestamp":1416574800,"obDateTime":"2014-11-21T14:00:00+01:00","ob":{"timestamp":1416574800,"dateTimeISO":"2014-11-21T14:00:00+01:00","tempC":25,"tempF":77,"dewpointC":2,"dewpointF":36,"humidity":22,"pressureMB":1023,"pressureIN":30.21,"spressureMB":972,"spressureIN":28.7,"altimeterMB":null,"altimeterIN":null,"windKTS":9,"windKPH":17,"windMPH":10,"windSpeedKTS":9,"windSpeedKPH":17,"windSpeedMPH":10,"windDirDEG":150,"windDir":"SSE","windGustKTS":null,"windGustKPH":null,"windGustMPH":null,"flightRule":"LIFR","visibilityKM":11.265408,"visibilityMI":7,"weather":"Mostly Sunny","weatherShort":"Mostly Sunny","weatherCoded":"::FW","weatherPrimary":"Mostly Sunny","weatherPrimaryCoded":"::FW","cloudsCoded":"FW","icon":"pcloudy.png","heatindexC":25,"heatindexF":77,"windchillC":25,"windchillF":77,"feelslikeC":25,"feelslikeF":77,"isDay":true,"sunrise":1416550787,"sunriseISO":"2014-11-21T07:19:47+01:00","sunset":1416588096,"sunsetISO":"2014-11-21T17:41:36+01:00","snowDepthCM":null,"snowDepthIN":null,"precipMM":null,"precipIN":null,"solradWM2":null,"sky":19,"light":73},"raw":"DAUG 211300Z 15009KT CAVOK 25\/02 Q1023"},{"id":"DAUI","loc":{"long":2.5166666666667,"lat":27.25},"place":{"name":"in salah north","state":"","country":"dz"},"profile":{"tz":"Africa\/Algiers","elevM":269,"elevFT":883},"obTimestamp":1416574800,"obDateTime":"2014-11-21T14:00:00+01:00","ob":{"timestamp":1416574800,"dateTimeISO":"2014-11-21T14:00:00+01:00","tempC":32,"tempF":90,"dewpointC":-3,"dewpointF":27,"humidity":10,"pressureMB":1018,"pressureIN":30.06,"spressureMB":988,"spressureIN":29.18,"altimeterMB":null,"altimeterIN":null,"windKTS":8,"windKPH":15,"windMPH":9,"windSpeedKTS":8,"windSpeedKPH":15,"windSpeedMPH":9,"windDirDEG":100,"windDir":"E","windGustKTS":null,"windGustKPH":null,"windGustMPH":null,"flightRule":"LIFR","visibilityKM":11.265408,"visibilityMI":7,"weather":"Mostly Sunny","weatherShort":"Mostly Sunny","weatherCoded":"::FW","weatherPrimary":"Mostly Sunny","weatherPrimaryCoded":"::FW","cloudsCoded":"FW","icon":"pcloudy.png","heatindexC":32,"heatindexF":90,"windchillC":32,"windchillF":90,"feelslikeC":32,"feelslikeF":90,"isDay":true,"sunrise":1416550505,"sunriseISO":"2014-11-21T07:15:05+01:00","sunset":1416589002,"sunsetISO":"2014-11-21T17:56:42+01:00","snowDepthCM":null,"snowDepthIN":null,"precipMM":null,"precipIN":null,"solradWM2":null,"sky":19,"light":74},"raw":"DAUI 211300Z 10008KT CAVOK 32\/M03 Q1018"},{"id":"DAUE","loc":{"long":2.8666666666667,"lat":30.566666666667},"place":{"name":"el golea","state":"","country":"dz"},"profile":{"tz":"Africa\/Algiers","elevM":397,"elevFT":1302},"obTimestamp":1416574800,"obDateTime":"2014-11-21T14:00:00+01:00","ob":{"timestamp":1416574800,"dateTimeISO":"2014-11-21T14:00:00+01:00","tempC":26,"tempF":79,"dewpointC":8,"dewpointF":46,"humidity":32,"pressureMB":1022,"pressureIN":30.18,"spressureMB":977,"spressureIN":28.85,"altimeterMB":null,"altimeterIN":null,"windKTS":8,"windKPH":15,"windMPH":9,"windSpeedKTS":8,"windSpeedKPH":15,"windSpeedMPH":9,"windDirDEG":120,"windDir":"ESE","windGustKTS":null,"windGustKPH":null,"windGustMPH":null,"flightRule":"LIFR","visibilityKM":11.265408,"visibilityMI":7,"weather":"Mostly Sunny","weatherShort":"Mostly Sunny","weatherCoded":"::FW","weatherPrimary":"Mostly Sunny","weatherPrimaryCoded":"::FW","cloudsCoded":"FW","icon":"pcloudy.png","heatindexC":26,"heatindexF":79,"windchillC":26,"windchillF":79,"feelslikeC":26,"feelslikeF":79,"isDay":true,"sunrise":1416550799,"sunriseISO":"2014-11-21T07:19:59+01:00","sunset":1416588540,"sunsetISO":"2014-11-21T17:49:00+01:00","snowDepthCM":null,"snowDepthIN":null,"precipMM":null,"precipIN":null,"solradWM2":null,"sky":19,"light":74},"raw":"DAUE 211300Z 12008KT CAVOK 26\/08 Q1022"},{"id":"DAUT","loc":{"long":0.26666666666667,"lat":29.25},"place":{"name":"timimoun","state":"","country":"dz"},"profile":{"tz":"Africa\/Algiers","elevM":312,"elevFT":1024},"obTimestamp":1416574800,"obDateTime":"2014-11-21T14:00:00+01:00","ob":{"timestamp":1416574800,"dateTimeISO":"2014-11-21T14:00:00+01:00","tempC":32,"tempF":90,"dewpointC":-4,"dewpointF":25,"humidity":9,"pressureMB":1016,"pressureIN":30,"spressureMB":981,"spressureIN":28.97,"altimeterMB":null,"altimeterIN":null,"windKTS":10,"windKPH":19,"windMPH":12,"windSpeedKTS":10,"windSpeedKPH":19,"windSpeedMPH":12,"windDirDEG":0,"windDir":"N","windGustKTS":null,"windGustKPH":null,"windGustMPH":null,"flightRule":"LIFR","visibilityKM":null,"visibilityMI":null,"weather":"Partly Cloudy","weatherShort":"Partly Cloudy","weatherCoded":"::SC","weatherPrimary":"Partly Cloudy","weatherPrimaryCoded":"::SC","cloudsCoded":"SC","icon":"pcloudy.png","heatindexC":32,"heatindexF":90,"windchillC":32,"windchillF":90,"feelslikeC":32,"feelslikeF":90,"isDay":true,"sunrise":1416551270,"sunriseISO":"2014-11-21T07:27:50+01:00","sunset":1416589317,"sunsetISO":"2014-11-21T18:01:57+01:00","snowDepthCM":null,"snowDepthIN":null,"precipMM":null,"precipIN":null,"solradWM2":null,"light":64,"sky":44},"raw":"DAUT 211300Z \/\/\/10KT 9999 SCT046 SCT120 32\/M04 Q1016"},{"id":"DAUU","loc":{"long":5.4,"lat":31.916666666667},"place":{"name":"ouargla","state":"","country":"dz"},"profile":{"tz":"Africa\/Algiers","elevM":141,"elevFT":463},"obTimestamp":1416574800,"obDateTime":"2014-11-21T14:00:00+01:00","ob":{"timestamp":1416574800,"dateTimeISO":"2014-11-21T14:00:00+01:00","tempC":28,"tempF":82,"dewpointC":2,"dewpointF":36,"humidity":19,"pressureMB":1022,"pressureIN":30.18,"spressureMB":1006,"spressureIN":29.71,"altimeterMB":null,"altimeterIN":null,"windKTS":0,"windKPH":0,"windMPH":0,"windSpeedKTS":0,"windSpeedKPH":0,"windSpeedMPH":0,"windDirDEG":0,"windDir":"N","windGustKTS":null,"windGustKPH":null,"windGustMPH":null,"flightRule":"LIFR","visibilityKM":11.265408,"visibilityMI":7,"weather":"Mostly Sunny","weatherShort":"Mostly Sunny","weatherCoded":"::FW","weatherPrimary":"Mostly Sunny","weatherPrimaryCoded":"::FW","cloudsCoded":"FW","icon":"pcloudy.png","heatindexC":28,"heatindexF":82,"windchillC":28,"windchillF":82,"feelslikeC":28,"feelslikeF":82,"isDay":true,"sunrise":1416550352,"sunriseISO":"2014-11-21T07:12:32+01:00","sunset":1416587771,"sunsetISO":"2014-11-21T17:36:11+01:00","snowDepthCM":null,"snowDepthIN":null,"precipMM":null,"precipIN":null,"solradWM2":null,"sky":19,"light":69},"raw":"DAUU 211300Z 00000KT CAVOK 28\/02 Q1022"},{"id":"DAEF","loc":{"long":7.55,"lat":28.433333333333},"place":{"name":"tinfouye","state":"","country":"dz"},"profile":{"tz":"Africa\/Algiers","elevM":472,"elevFT":1549},"obTimestamp":1416574800,"obDateTime":"2014-11-21T14:00:00+01:00","ob":{"timestamp":1416574800,"dateTimeISO":"2014-11-21T14:00:00+01:00","tempC":27,"tempF":81,"dewpointC":1,"dewpointF":34,"humidity":18,"pressureMB":1022,"pressureIN":30.18,"spressureMB":969,"spressureIN":28.61,"altimeterMB":null,"altimeterIN":null,"windKTS":4,"windKPH":7,"windMPH":5,"windSpeedKTS":4,"windSpeedKPH":7,"windSpeedMPH":5,"windDirDEG":80,"windDir":"E","windGustKTS":null,"windGustKPH":null,"windGustMPH":null,"flightRule":"LIFR","visibilityKM":11.265408,"visibilityMI":7,"weather":"Mostly Sunny","weatherShort":"Mostly Sunny","weatherCoded":"::FW","weatherPrimary":"Mostly Sunny","weatherPrimaryCoded":"::FW","cloudsCoded":"FW","icon":"pcloudy.png","heatindexC":27,"heatindexF":81,"windchillC":27,"windchillF":81,"feelslikeC":27,"feelslikeF":81,"isDay":true,"sunrise":1416549428,"sunriseISO":"2014-11-21T06:57:08+01:00","sunset":1416587662,"sunsetISO":"2014-11-21T17:34:22+01:00","snowDepthCM":null,"snowDepthIN":null,"precipMM":null,"precipIN":null,"solradWM2":null,"sky":19,"light":68},"raw":"DAEF 211300Z 08004KT CAVOK 27\/01 Q1022"},{"id":"DAOI","loc":{"long":1.3166666666667,"lat":36.216666666667},"place":{"name":"chlef","state":"","country":"dz"},"profile":{"tz":"Africa\/Algiers","elevM":143,"elevFT":469},"obTimestamp":1416574800,"obDateTime":"2014-11-21T14:00:00+01:00","ob":{"timestamp":1416574800,"dateTimeISO":"2014-11-21T14:00:00+01:00","tempC":26,"tempF":79,"dewpointC":9,"dewpointF":48,"humidity":34,"pressureMB":1017,"pressureIN":30.03,"spressureMB":1001,"spressureIN":29.56,"altimeterMB":null,"altimeterIN":null,"windKTS":10,"windKPH":19,"windMPH":12,"windSpeedKTS":10,"windSpeedKPH":19,"windSpeedMPH":12,"windDirDEG":80,"windDir":"E","windGustKTS":null,"windGustKPH":null,"windGustMPH":null,"flightRule":"LIFR","visibilityKM":11.265408,"visibilityMI":7,"weather":"Mostly Sunny","weatherShort":"Mostly Sunny","weatherCoded":"::FW","weatherPrimary":"Mostly Sunny","weatherPrimaryCoded":"::FW","cloudsCoded":"FW","icon":"pcloudy.png","heatindexC":26,"heatindexF":79,"windchillC":26,"windchillF":79,"feelslikeC":26,"feelslikeF":79,"isDay":true,"sunrise":1416551883,"sunriseISO":"2014-11-21T07:38:03+01:00","sunset":1416588200,"sunsetISO":"2014-11-21T17:43:20+01:00","snowDepthCM":null,"snowDepthIN":null,"precipMM":null,"precipIN":null,"solradWM2":null,"sky":19,"light":74},"raw":"DAOI 211300Z 08010KT CAVOK 26\/09 Q1017"},{"id":"DAUK","loc":{"long":6.1166666666667,"lat":33.083333333333},"place":{"name":"touggourt\/sidi m","state":"","country":"dz"},"profile":{"tz":"Africa\/Algiers","elevM":85,"elevFT":279},"obTimestamp":1416574800,"obDateTime":"2014-11-21T14:00:00+01:00","ob":{"timestamp":1416574800,"dateTimeISO":"2014-11-21T14:00:00+01:00","tempC":25,"tempF":77,"dewpointC":7,"dewpointF":45,"humidity":32,"pressureMB":1012,"pressureIN":29.88,"spressureMB":1002,"spressureIN":29.59,"altimeterMB":null,"altimeterIN":null,"windKTS":0,"windKPH":0,"windMPH":0,"windSpeedKTS":0,"windSpeedKPH":0,"windSpeedMPH":0,"windDirDEG":0,"windDir":"N","windGustKTS":null,"windGustKPH":null,"windGustMPH":null,"flightRule":"LIFR","visibilityKM":11.265408,"visibilityMI":7,"weather":"Mostly Sunny","weatherShort":"Mostly Sunny","weatherCoded":"::FW","weatherPrimary":"Mostly Sunny","weatherPrimaryCoded":"::FW","cloudsCoded":"FW","icon":"pcloudy.png","heatindexC":25,"heatindexF":77,"windchillC":25,"windchillF":77,"feelslikeC":25,"feelslikeF":77,"isDay":true,"sunrise":1416550323,"sunriseISO":"2014-11-21T07:12:03+01:00","sunset":1416587455,"sunsetISO":"2014-11-21T17:30:55+01:00","snowDepthCM":null,"snowDepthIN":null,"precipMM":null,"precipIN":null,"solradWM2":null,"sky":19,"light":68},"raw":"DAUK 211300Z 00000KT CAVOK 25\/07 Q1012"},{"id":"DAAD","loc":{"long":4.2,"lat":35.316666666667},"place":{"name":"bou-saada","state":"","country":"dz"},"profile":{"tz":"Africa\/Algiers","elevM":461,"elevFT":1512},"obTimestamp":1416574800,"obDateTime":"2014-11-21T14:00:00+01:00","ob":{"timestamp":1416574800,"dateTimeISO":"2014-11-21T14:00:00+01:00","tempC":22,"tempF":72,"dewpointC":6,"dewpointF":43,"humidity":36,"pressureMB":1022,"pressureIN":30.18,"spressureMB":969,"spressureIN":28.61,"altimeterMB":null,"altimeterIN":null,"windKTS":0,"windKPH":0,"windMPH":0,"windSpeedKTS":0,"windSpeedKPH":0,"windSpeedMPH":0,"windDirDEG":0,"windDir":"N","windGustKTS":null,"windGustKPH":null,"windGustMPH":null,"flightRule":"LIFR","visibilityKM":11.265408,"visibilityMI":7,"weather":"Mostly Sunny","weatherShort":"Mostly Sunny","weatherCoded":"::FW","weatherPrimary":"Mostly Sunny","weatherPrimaryCoded":"::FW","cloudsCoded":"FW","icon":"pcloudy.png","heatindexC":22,"heatindexF":72,"windchillC":22,"windchillF":72,"feelslikeC":22,"feelslikeF":72,"isDay":true,"sunrise":1416551070,"sunriseISO":"2014-11-21T07:24:30+01:00","sunset":1416587629,"sunsetISO":"2014-11-21T17:33:49+01:00","snowDepthCM":null,"snowDepthIN":null,"precipMM":null,"precipIN":null,"solradWM2":null,"sky":19,"light":69},"raw":"DAAD 211300Z 00000KT CAVOK 22\/06 Q1022"},{"id":"DAUO","loc":{"long":6.7833333333333,"lat":33.5},"place":{"name":"el oued\/guemer","state":"","country":"dz"},"profile":{"tz":"Africa\/Algiers","elevM":63,"elevFT":207},"obTimestamp":1416574800,"obDateTime":"2014-11-21T14:00:00+01:00","ob":{"timestamp":1416574800,"dateTimeISO":"2014-11-21T14:00:00+01:00","tempC":28,"tempF":82,"dewpointC":9,"dewpointF":48,"humidity":30,"pressureMB":1021,"pressureIN":30.15,"spressureMB":1014,"spressureIN":29.94,"altimeterMB":null,"altimeterIN":null,"windKTS":null,"windKPH":null,"windMPH":null,"windSpeedKTS":null,"windSpeedKPH":null,"windSpeedMPH":null,"windDirDEG":0,"windDir":"N","windGustKTS":null,"windGustKPH":null,"windGustMPH":null,"flightRule":"LIFR","visibilityKM":11.265408,"visibilityMI":7,"weather":"Mostly Sunny","weatherShort":"Mostly Sunny","weatherCoded":"::FW","weatherPrimary":"Mostly Sunny","weatherPrimaryCoded":"::FW","cloudsCoded":"FW","icon":"pcloudy.png","heatindexC":28,"heatindexF":82,"windchillC":28,"windchillF":82,"feelslikeC":28,"feelslikeF":82,"isDay":true,"sunrise":1416550216,"sunriseISO":"2014-11-21T07:10:16+01:00","sunset":1416587243,"sunsetISO":"2014-11-21T17:27:23+01:00","snowDepthCM":null,"snowDepthIN":null,"precipMM":null,"precipIN":null,"solradWM2":null,"sky":19,"light":68},"raw":"DAUO 211300Z \/\/\/\/\/KT CAVOK 28\/09 Q1021"},{"id":"DAUA","loc":{"long":-0.18333333333333,"lat":27.833333333333},"place":{"name":"adrar\/touat","state":"","country":"dz"},"profile":{"tz":"Africa\/Algiers","elevM":263,"elevFT":863},"obTimestamp":1416574800,"obDateTime":"2014-11-21T14:00:00+01:00","ob":{"timestamp":1416574800,"dateTimeISO":"2014-11-21T14:00:00+01:00","tempC":33,"tempF":91,"dewpointC":5,"dewpointF":41,"humidity":17,"pressureMB":1015,"pressureIN":29.97,"spressureMB":986,"spressureIN":29.12,"altimeterMB":null,"altimeterIN":null,"windKTS":18,"windKPH":33,"windMPH":21,"windSpeedKTS":18,"windSpeedKPH":33,"windSpeedMPH":21,"windDirDEG":120,"windDir":"ESE","windGustKTS":null,"windGustKPH":null,"windGustMPH":null,"flightRule":"LIFR","visibilityKM":null,"visibilityMI":null,"weather":"Partly Cloudy","weatherShort":"Partly Cloudy","weatherCoded":"::SC","weatherPrimary":"Partly Cloudy","weatherPrimaryCoded":"::SC","cloudsCoded":"SC","icon":"pcloudy.png","heatindexC":33,"heatindexF":91,"windchillC":33,"windchillF":91,"feelslikeC":33,"feelslikeF":91,"isDay":true,"sunrise":1416551218,"sunriseISO":"2014-11-21T07:26:58+01:00","sunset":1416589585,"sunsetISO":"2014-11-21T18:06:25+01:00","snowDepthCM":null,"snowDepthIN":null,"precipMM":null,"precipIN":null,"solradWM2":null,"light":65,"sky":44},"raw":"DAUA 211300Z 12018KT 9999 FEW046 SCT150 33\/05 Q1015"},{"id":"DAOF","loc":{"long":-8.1666666666667,"lat":27.7},"place":{"name":"tindouf","state":"","country":"dz"},"profile":{"tz":"Africa\/Algiers","elevM":431,"elevFT":1414},"obTimestamp":1416574800,"obDateTime":"2014-11-21T14:00:00+01:00","ob":{"timestamp":1416574800,"dateTimeISO":"2014-11-21T14:00:00+01:00","tempC":22,"tempF":72,"dewpointC":11,"dewpointF":52,"humidity":50,"pressureMB":1010,"pressureIN":29.83,"spressureMB":961,"spressureIN":28.38,"altimeterMB":null,"altimeterIN":null,"windKTS":18,"windKPH":33,"windMPH":21,"windSpeedKTS":18,"windSpeedKPH":33,"windSpeedMPH":21,"windDirDEG":130,"windDir":"SE","windGustKTS":null,"windGustKPH":null,"windGustMPH":null,"flightRule":"LIFR","visibilityKM":8,"visibilityMI":4.97,"weather":"Mostly Cloudy","weatherShort":"Mostly Cloudy","weatherCoded":"::BK","weatherPrimary":"Mostly Cloudy","weatherPrimaryCoded":"::BK","cloudsCoded":"BK","icon":"mcloudy.png","heatindexC":22,"heatindexF":72,"windchillC":22,"windchillF":72,"feelslikeC":22,"feelslikeF":72,"isDay":true,"sunrise":1416553120,"sunriseISO":"2014-11-21T07:58:40+01:00","sunset":1416591516,"sunsetISO":"2014-11-21T18:38:36+01:00","snowDepthCM":null,"snowDepthIN":null,"precipMM":null,"precipIN":null,"solradWM2":null,"light":67,"sky":81},"raw":"DAOF 211300Z 13018KT 8000 FEW030CB SCT046 BKN100 22\/11 Q1010"},{"id":"DAOB","loc":{"long":1.4666666666667,"lat":35.333333333333},"place":{"name":"tiaret","state":"","country":"dz"},"profile":{"tz":"Africa\/Algiers","elevM":989,"elevFT":3245},"obTimestamp":1416574800,"obDateTime":"2014-11-21T14:00:00+01:00","ob":{"timestamp":1416574800,"dateTimeISO":"2014-11-21T14:00:00+01:00","tempC":23,"tempF":73,"dewpointC":7,"dewpointF":45,"humidity":36,"pressureMB":1022,"pressureIN":30.18,"spressureMB":913,"spressureIN":26.96,"altimeterMB":null,"altimeterIN":null,"windKTS":17,"windKPH":31,"windMPH":20,"windSpeedKTS":17,"windSpeedKPH":31,"windSpeedMPH":20,"windDirDEG":160,"windDir":"SSE","windGustKTS":null,"windGustKPH":null,"windGustMPH":null,"flightRule":"LIFR","visibilityKM":null,"visibilityMI":null,"weather":"Partly Cloudy","weatherShort":"Partly Cloudy","weatherCoded":"::SC","weatherPrimary":"Partly Cloudy","weatherPrimaryCoded":"::SC","cloudsCoded":"SC","icon":"pcloudy.png","heatindexC":23,"heatindexF":73,"windchillC":23,"windchillF":73,"feelslikeC":23,"feelslikeF":73,"isDay":true,"sunrise":1416551729,"sunriseISO":"2014-11-21T07:35:29+01:00","sunset":1416588282,"sunsetISO":"2014-11-21T17:44:42+01:00","snowDepthCM":null,"snowDepthIN":null,"precipMM":null,"precipIN":null,"solradWM2":null,"light":64,"sky":44},"raw":"DAOB 211300Z 16017KT 9999 FEW026 SCT216 23\/07 Q1022"},{"id":"DABT","loc":{"long":6.3166666666667,"lat":35.75},"place":{"name":"batna","state":"","country":"dz"},"profile":{"tz":"Africa\/Algiers","elevM":1052,"elevFT":3451},"obTimestamp":1416574800,"obDateTime":"2014-11-21T14:00:00+01:00","ob":{"timestamp":1416574800,"dateTimeISO":"2014-11-21T14:00:00+01:00","tempC":26,"tempF":79,"dewpointC":-1,"dewpointF":30,"humidity":17,"pressureMB":1023,"pressureIN":30.21,"spressureMB":908,"spressureIN":26.81,"altimeterMB":null,"altimeterIN":null,"windKTS":14,"windKPH":26,"windMPH":16,"windSpeedKTS":14,"windSpeedKPH":26,"windSpeedMPH":16,"windDirDEG":250,"windDir":"WSW","windGustKTS":null,"windGustKPH":null,"windGustMPH":null,"flightRule":"LIFR","visibilityKM":11.265408,"visibilityMI":7,"weather":"Mostly Sunny","weatherShort":"Mostly Sunny","weatherCoded":"::FW","weatherPrimary":"Mostly Sunny","weatherPrimaryCoded":"::FW","cloudsCoded":"FW","icon":"pcloudy.png","heatindexC":26,"heatindexF":79,"windchillC":26,"windchillF":79,"feelslikeC":26,"feelslikeF":79,"isDay":true,"sunrise":1416550620,"sunriseISO":"2014-11-21T07:17:00+01:00","sunset":1416587063,"sunsetISO":"2014-11-21T17:24:23+01:00","snowDepthCM":null,"snowDepthIN":null,"precipMM":null,"precipIN":null,"solradWM2":null,"sky":19,"light":68},"raw":"DABT 211300Z 25014KT CAVOK 26\/M01 Q1023"},{"id":"DAEN","loc":{"long":6.7166666666667,"lat":29.733333333333},"place":{"name":"rhourd nouss","state":"","country":"dz"},"profile":{"tz":"Africa\/Algiers","elevM":252,"elevFT":827},"obTimestamp":1416574800,"obDateTime":"2014-11-21T14:00:00+01:00","ob":{"timestamp":1416574800,"dateTimeISO":"2014-11-21T14:00:00+01:00","tempC":27,"tempF":81,"dewpointC":2,"dewpointF":36,"humidity":20,"pressureMB":1021,"pressureIN":30.15,"spressureMB":992,"spressureIN":29.29,"altimeterMB":null,"altimeterIN":null,"windKTS":12,"windKPH":22,"windMPH":14,"windSpeedKTS":12,"windSpeedKPH":22,"windSpeedMPH":14,"windDirDEG":90,"windDir":"E","windGustKTS":null,"windGustKPH":null,"windGustMPH":null,"flightRule":"LIFR","visibilityKM":11.265408,"visibilityMI":7,"weather":"Mostly Sunny","weatherShort":"Mostly Sunny","weatherCoded":"::FW","weatherPrimary":"Mostly Sunny","weatherPrimaryCoded":"::FW","cloudsCoded":"FW","icon":"pcloudy.png","heatindexC":27,"heatindexF":81,"windchillC":27,"windchillF":81,"feelslikeC":27,"feelslikeF":81,"isDay":true,"sunrise":1416549777,"sunriseISO":"2014-11-21T07:02:57+01:00","sunset":1416587714,"sunsetISO":"2014-11-21T17:35:14+01:00","snowDepthCM":null,"snowDepthIN":null,"precipMM":null,"precipIN":null,"solradWM2":null,"sky":19,"light":68},"raw":"DAEN 211300Z 09012KT CAVOK 27\/02 Q1021"},{"id":"DAUZ","loc":{"long":9.6166666666667,"lat":28.05},"place":{"name":"in amenas\/zarzai","state":"","country":"dz"},"profile":{"tz":"Africa\/Algiers","elevM":562,"elevFT":1844},"obTimestamp":1416574800,"obDateTime":"2014-11-21T14:00:00+01:00","ob":{"timestamp":1416574800,"dateTimeISO":"2014-11-21T14:00:00+01:00","tempC":26,"tempF":79,"dewpointC":3,"dewpointF":37,"humidity":23,"pressureMB":1022,"pressureIN":30.18,"spressureMB":959,"spressureIN":28.32,"altimeterMB":null,"altimeterIN":null,"windKTS":7,"windKPH":13,"windMPH":8,"windSpeedKTS":7,"windSpeedKPH":13,"windSpeedMPH":8,"windDirDEG":130,"windDir":"SE","windGustKTS":null,"windGustKPH":null,"windGustMPH":null,"flightRule":"LIFR","visibilityKM":11.265408,"visibilityMI":7,"weather":"Mostly Sunny","weatherShort":"Mostly Sunny","weatherCoded":"::FW","weatherPrimary":"Mostly Sunny","weatherPrimaryCoded":"::FW","cloudsCoded":"FW","icon":"pcloudy.png","heatindexC":26,"heatindexF":79,"windchillC":26,"windchillF":79,"feelslikeC":26,"feelslikeF":79,"isDay":true,"sunrise":1416548889,"sunriseISO":"2014-11-21T06:48:09+01:00","sunset":1416587210,"sunsetISO":"2014-11-21T17:26:50+01:00","snowDepthCM":null,"snowDepthIN":null,"precipMM":null,"precipIN":null,"solradWM2":null,"sky":19,"light":67},"raw":"DAUZ 211300Z 13007KT 090V170 CAVOK 26\/03 Q1022"},{"id":"DAAJ","loc":{"long":9.4666666666667,"lat":24.283333333333},"place":{"name":"djanet\/tiska","state":"","country":"dz"},"profile":{"tz":"Africa\/Algiers","elevM":968,"elevFT":3176},"obTimestamp":1416574800,"obDateTime":"2014-11-21T14:00:00+01:00","ob":{"timestamp":1416574800,"dateTimeISO":"2014-11-21T14:00:00+01:00","tempC":27,"tempF":81,"dewpointC":8,"dewpointF":46,"humidity":30,"pressureMB":1023,"pressureIN":30.21,"spressureMB":917,"spressureIN":27.08,"altimeterMB":null,"altimeterIN":null,"windKTS":6,"windKPH":11,"windMPH":7,"windSpeedKTS":6,"windSpeedKPH":11,"windSpeedMPH":7,"windDirDEG":290,"windDir":"WNW","windGustKTS":null,"windGustKPH":null,"windGustMPH":null,"flightRule":"LIFR","visibilityKM":11.265408,"visibilityMI":7,"weather":"Mostly Sunny","weatherShort":"Mostly Sunny","weatherCoded":"::FW","weatherPrimary":"Mostly Sunny","weatherPrimaryCoded":"::FW","cloudsCoded":"FW","icon":"pcloudy.png","heatindexC":27,"heatindexF":81,"windchillC":27,"windchillF":81,"feelslikeC":27,"feelslikeF":81,"isDay":true,"sunrise":1416548518,"sunriseISO":"2014-11-21T06:41:58+01:00","sunset":1416587653,"sunsetISO":"2014-11-21T17:34:13+01:00","snowDepthCM":null,"snowDepthIN":null,"precipMM":null,"precipIN":null,"solradWM2":null,"sky":19,"light":67},"raw":"DAAJ 211300Z 29006KT CAVOK 27\/08 Q1023"},{"id":"DAAG","loc":{"long":3.2166666666667,"lat":36.716666666667},"place":{"name":"dar-el-beida\/hou","state":"","country":"dz"},"profile":{"tz":"Africa\/Algiers","elevM":25,"elevFT":82},"obTimestamp":1416576600,"obDateTime":"2014-11-21T14:30:00+01:00","ob":{"timestamp":1416576600,"dateTimeISO":"2014-11-21T14:30:00+01:00","tempC":30,"tempF":86,"dewpointC":10,"dewpointF":50,"humidity":29,"pressureMB":1017,"pressureIN":30.03,"spressureMB":1014,"spressureIN":29.94,"altimeterMB":null,"altimeterIN":null,"windKTS":5,"windKPH":9,"windMPH":6,"windSpeedKTS":5,"windSpeedKPH":9,"windSpeedMPH":6,"windDirDEG":220,"windDir":"SW","windGustKTS":null,"windGustKPH":null,"windGustMPH":null,"flightRule":"LIFR","visibilityKM":11.265408,"visibilityMI":7,"weather":"Mostly Sunny","weatherShort":"Mostly Sunny","weatherCoded":"::FW","weatherPrimary":"Mostly Sunny","weatherPrimaryCoded":"::FW","cloudsCoded":"FW","icon":"pcloudy.png","heatindexC":30,"heatindexF":86,"windchillC":30,"windchillF":86,"feelslikeC":30,"feelslikeF":86,"isDay":true,"sunrise":1416551495,"sunriseISO":"2014-11-21T07:31:35+01:00","sunset":1416587676,"sunsetISO":"2014-11-21T17:34:36+01:00","snowDepthCM":null,"snowDepthIN":null,"precipMM":null,"precipIN":null,"solradWM2":null,"sky":19,"light":65},"raw":"DAAG 211330Z 22005KT CAVOK 30\/10 Q1017"},{"id":"DAON","loc":{"long":-1.4666666666667,"lat":35.016666666667},"place":{"name":"tlemcen\/zenata","state":"","country":"dz"},"profile":{"tz":"Africa\/Algiers","elevM":247,"elevFT":810},"obTimestamp":1416576600,"obDateTime":"2014-11-21T14:30:00+01:00","ob":{"timestamp":1416576600,"dateTimeISO":"2014-11-21T14:30:00+01:00","tempC":29,"tempF":84,"dewpointC":3,"dewpointF":37,"humidity":19,"pressureMB":1015,"pressureIN":29.97,"spressureMB":987,"spressureIN":29.15,"altimeterMB":null,"altimeterIN":null,"windKTS":20,"windKPH":37,"windMPH":23,"windSpeedKTS":20,"windSpeedKPH":37,"windSpeedMPH":23,"windDirDEG":200,"windDir":"SSW","windGustKTS":null,"windGustKPH":null,"windGustMPH":null,"flightRule":"LIFR","visibilityKM":7,"visibilityMI":4.35,"weather":"Mostly Cloudy","weatherShort":"Mostly Cloudy","weatherCoded":"::BK","weatherPrimary":"Mostly Cloudy","weatherPrimaryCoded":"::BK","cloudsCoded":"BK","icon":"mcloudy.png","heatindexC":29,"heatindexF":84,"windchillC":29,"windchillF":84,"feelslikeC":29,"feelslikeF":84,"isDay":true,"sunrise":1416552392,"sunriseISO":"2014-11-21T07:46:32+01:00","sunset":1416589028,"sunsetISO":"2014-11-21T17:57:08+01:00","snowDepthCM":null,"snowDepthIN":null,"precipMM":null,"precipIN":null,"solradWM2":null,"light":59,"sky":81},"raw":"DAON 211330Z 20020KT 7000 FEW030CB SCT100 BKN233 29\/03 Q1015"},{"id":"DABB","loc":{"long":7.8166666666667,"lat":36.816666666667},"place":{"name":"annaba\/el mellah","state":"","country":"dz"},"profile":{"tz":"Africa\/Algiers","elevM":4,"elevFT":13},"obTimestamp":1416576600,"obDateTime":"2014-11-21T14:30:00+01:00","ob":{"timestamp":1416576600,"dateTimeISO":"2014-11-21T14:30:00+01:00","tempC":25,"tempF":77,"dewpointC":10,"dewpointF":50,"humidity":39,"pressureMB":1017,"pressureIN":30.03,"spressureMB":1017,"spressureIN":30.03,"altimeterMB":null,"altimeterIN":null,"windKTS":7,"windKPH":13,"windMPH":8,"windSpeedKTS":7,"windSpeedKPH":13,"windSpeedMPH":8,"windDirDEG":60,"windDir":"ENE","windGustKTS":null,"windGustKPH":null,"windGustMPH":null,"flightRule":"LIFR","visibilityKM":11.265408,"visibilityMI":7,"weather":"Mostly Sunny","weatherShort":"Mostly Sunny","weatherCoded":"::FW","weatherPrimary":"Mostly Sunny","weatherPrimaryCoded":"::FW","cloudsCoded":"FW","icon":"pcloudy.png","heatindexC":25,"heatindexF":77,"windchillC":25,"windchillF":77,"feelslikeC":25,"feelslikeF":77,"isDay":true,"sunrise":1416550404,"sunriseISO":"2014-11-21T07:13:24+01:00","sunset":1416586559,"sunsetISO":"2014-11-21T17:15:59+01:00","snowDepthCM":null,"snowDepthIN":null,"precipMM":null,"precipIN":null,"solradWM2":null,"sky":19,"light":63},"raw":"DABB 211330Z 06007KT CAVOK 25\/10 Q1017"},{"id":"DABS","loc":{"long":8.1166666666667,"lat":35.433333333333},"place":{"name":"tebessa","state":"","country":"dz"},"profile":{"tz":"Africa\/Algiers","elevM":813,"elevFT":2667},"obTimestamp":1416576600,"obDateTime":"2014-11-21T14:30:00+01:00","ob":{"timestamp":1416576600,"dateTimeISO":"2014-11-21T14:30:00+01:00","tempC":26,"tempF":79,"dewpointC":4,"dewpointF":39,"humidity":24,"pressureMB":1023,"pressureIN":30.21,"spressureMB":933,"spressureIN":27.55,"altimeterMB":null,"altimeterIN":null,"windKTS":10,"windKPH":19,"windMPH":12,"windSpeedKTS":10,"windSpeedKPH":19,"windSpeedMPH":12,"windDirDEG":320,"windDir":"NW","windGustKTS":null,"windGustKPH":null,"windGustMPH":null,"flightRule":"LIFR","visibilityKM":11.265408,"visibilityMI":7,"weather":"Mostly Sunny","weatherShort":"Mostly Sunny","weatherCoded":"::FW","weatherPrimary":"Mostly Sunny","weatherPrimaryCoded":"::FW","cloudsCoded":"FW","icon":"pcloudy.png","heatindexC":26,"heatindexF":79,"windchillC":26,"windchillF":79,"feelslikeC":26,"feelslikeF":79,"isDay":true,"sunrise":1416550145,"sunriseISO":"2014-11-21T07:09:05+01:00","sunset":1416586673,"sunsetISO":"2014-11-21T17:17:53+01:00","snowDepthCM":null,"snowDepthIN":null,"precipMM":null,"precipIN":null,"solradWM2":null,"sky":19,"light":63},"raw":"DABS 211330Z 32010KT CAVOK 26\/04 Q1023"},{"id":"DABC","loc":{"long":6.6166666666667,"lat":36.266666666667},"place":{"name":"constantine\/el b","state":"","country":"dz"},"profile":{"tz":"Africa\/Algiers","elevM":694,"elevFT":2277},"obTimestamp":1416576600,"obDateTime":"2014-11-21T14:30:00+01:00","ob":{"timestamp":1416576600,"dateTimeISO":"2014-11-21T14:30:00+01:00","tempC":27,"tempF":81,"dewpointC":4,"dewpointF":39,"humidity":23,"pressureMB":1022,"pressureIN":30.18,"spressureMB":945,"spressureIN":27.91,"altimeterMB":null,"altimeterIN":null,"windKTS":11,"windKPH":20,"windMPH":13,"windSpeedKTS":11,"windSpeedKPH":20,"windSpeedMPH":13,"windDirDEG":260,"windDir":"W","windGustKTS":null,"windGustKPH":null,"windGustMPH":null,"flightRule":"LIFR","visibilityKM":11.265408,"visibilityMI":7,"weather":"Mostly Sunny","weatherShort":"Mostly Sunny","weatherCoded":"::FW","weatherPrimary":"Mostly Sunny","weatherPrimaryCoded":"::FW","cloudsCoded":"FW","icon":"pcloudy.png","heatindexC":27,"heatindexF":81,"windchillC":27,"windchillF":81,"feelslikeC":27,"feelslikeF":81,"isDay":true,"sunrise":1416550617,"sunriseISO":"2014-11-21T07:16:57+01:00","sunset":1416586922,"sunsetISO":"2014-11-21T17:22:02+01:00","snowDepthCM":null,"snowDepthIN":null,"precipMM":null,"precipIN":null,"solradWM2":null,"sky":19,"light":64},"raw":"DABC 211330Z 26011KT CAVOK 27\/04 Q1022"},{"id":"DAUH","loc":{"long":6.15,"lat":31.666666666667},"place":{"name":"hassi-messaoud\/i","state":"","country":"dz"},"profile":{"tz":"Africa\/Algiers","elevM":142,"elevFT":466},"obTimestamp":1416576600,"obDateTime":"2014-11-21T14:30:00+01:00","ob":{"timestamp":1416576600,"dateTimeISO":"2014-11-21T14:30:00+01:00","tempC":29,"tempF":84,"dewpointC":6,"dewpointF":43,"humidity":23,"pressureMB":1021,"pressureIN":30.15,"spressureMB":1005,"spressureIN":29.68,"altimeterMB":null,"altimeterIN":null,"windKTS":6,"windKPH":11,"windMPH":7,"windSpeedKTS":6,"windSpeedKPH":11,"windSpeedMPH":7,"windDirDEG":100,"windDir":"E","windGustKTS":null,"windGustKPH":null,"windGustMPH":null,"flightRule":"LIFR","visibilityKM":11.265408,"visibilityMI":7,"weather":"Mostly Sunny","weatherShort":"Mostly Sunny","weatherCoded":"::FW","weatherPrimary":"Mostly Sunny","weatherPrimaryCoded":"::FW","cloudsCoded":"FW","icon":"pcloudy.png","heatindexC":29,"heatindexF":84,"windchillC":29,"windchillF":84,"feelslikeC":29,"feelslikeF":84,"isDay":true,"sunrise":1416550142,"sunriseISO":"2014-11-21T07:09:02+01:00","sunset":1416587621,"sunsetISO":"2014-11-21T17:33:41+01:00","snowDepthCM":null,"snowDepthIN":null,"precipMM":null,"precipIN":null,"solradWM2":null,"sky":19,"light":65},"raw":"DAUH 211330Z 10006KT CAVOK 29\/06 Q1021"},{"id":"DAOO","loc":{"long":-0.6,"lat":35.616666666667},"place":{"name":"oran\/es senia","state":"","country":"dz"},"profile":{"tz":"Africa\/Algiers","elevM":90,"elevFT":295},"obTimestamp":1416576600,"obDateTime":"2014-11-21T14:30:00+01:00","ob":{"timestamp":1416576600,"dateTimeISO":"2014-11-21T14:30:00+01:00","tempC":27,"tempF":81,"dewpointC":7,"dewpointF":45,"humidity":28,"pressureMB":1016,"pressureIN":30,"spressureMB":1006,"spressureIN":29.71,"altimeterMB":null,"altimeterIN":null,"windKTS":4,"windKPH":7,"windMPH":5,"windSpeedKTS":4,"windSpeedKPH":7,"windSpeedMPH":5,"windDirDEG":220,"windDir":"SW","windGustKTS":null,"windGustKPH":null,"windGustMPH":null,"flightRule":"LIFR","visibilityKM":null,"visibilityMI":null,"weather":"Mostly Cloudy","weatherShort":"Mostly Cloudy","weatherCoded":"::BK","weatherPrimary":"Mostly Cloudy","weatherPrimaryCoded":"::BK","cloudsCoded":"BK","icon":"mcloudy.png","heatindexC":27,"heatindexF":81,"windchillC":27,"windchillF":81,"feelslikeC":27,"feelslikeF":81,"isDay":true,"sunrise":1416552263,"sunriseISO":"2014-11-21T07:44:23+01:00","sunset":1416588740,"sunsetISO":"2014-11-21T17:52:20+01:00","snowDepthCM":null,"snowDepthIN":null,"precipMM":null,"precipIN":null,"solradWM2":null,"light":58,"sky":81},"raw":"DAOO 211330Z 22004KT 9999 SCT033 SCT100 BKN233 27\/07 Q1016"},{"id":"DAAT","loc":{"long":5.4666666666667,"lat":22.816666666667},"place":{"name":"tamanrasset\/ague","state":"","country":"dz"},"profile":{"tz":"Africa\/Algiers","elevM":1377,"elevFT":4518},"obTimestamp":1416576600,"obDateTime":"2014-11-21T14:30:00+01:00","ob":{"timestamp":1416576600,"dateTimeISO":"2014-11-21T14:30:00+01:00","tempC":26,"tempF":79,"dewpointC":-1,"dewpointF":30,"humidity":17,"pressureMB":1023,"pressureIN":30.21,"spressureMB":876,"spressureIN":25.87,"altimeterMB":null,"altimeterIN":null,"windKTS":4,"windKPH":7,"windMPH":5,"windSpeedKTS":4,"windSpeedKPH":7,"windSpeedMPH":5,"windDirDEG":140,"windDir":"SE","windGustKTS":null,"windGustKPH":null,"windGustMPH":null,"flightRule":"LIFR","visibilityKM":11.265408,"visibilityMI":7,"weather":"Mostly Sunny","weatherShort":"Mostly Sunny","weatherCoded":"::FW","weatherPrimary":"Mostly Sunny","weatherPrimaryCoded":"::FW","cloudsCoded":"FW","icon":"pcloudy.png","heatindexC":26,"heatindexF":79,"windchillC":26,"windchillF":79,"feelslikeC":26,"feelslikeF":79,"isDay":true,"sunrise":1416549326,"sunriseISO":"2014-11-21T06:55:26+01:00","sunset":1416588765,"sunsetISO":"2014-11-21T17:52:45+01:00","snowDepthCM":null,"snowDepthIN":null,"precipMM":null,"precipIN":null,"solradWM2":null,"sky":19,"light":66},"raw":"DAAT 211330Z 14004KT CAVOK 26\/M01 Q1023"}]}