{"success":true,"error":null,"response":[{"id":"TFFF","loc":{"long":-61,"lat":14.6},"place":{"name":"le lamentin\/mart","state":"","country":"mq"},"profile":{"tz":"America\/Martinique","elevM":5,"elevFT":16},"obTimestamp":1416576600,"obDateTime":"2014-11-21T09:30:00-04:00","ob":{"timestamp":1416576600,"dateTimeISO":"2014-11-21T09:30:00-04:00","tempC":25,"tempF":77,"dewpointC":24,"dewpointF":75,"humidity":94,"pressureMB":1015,"pressureIN":29.97,"spressureMB":1014,"spressureIN":29.94,"altimeterMB":null,"altimeterIN":null,"windKTS":9,"windKPH":17,"windMPH":10,"windSpeedKTS":9,"windSpeedKPH":17,"windSpeedMPH":10,"windDirDEG":70,"windDir":"ENE","windGustKTS":null,"windGustKPH":null,"windGustMPH":null,"flightRule":"MVFR","visibilityKM":null,"visibilityMI":null,"weather":"Mostly Cloudy","weatherShort":"Mostly Cloudy","weatherCoded":"::BK","weatherPrimary":"Mostly Cloudy","weatherPrimaryCoded":"::BK","cloudsCoded":"BK","icon":"mcloudy.png","heatindexC":25,"heatindexF":77,"windchillC":25,"windchillF":77,"feelslikeC":25,"feelslikeF":77,"isDay":true,"sunrise":1416564493,"sunriseISO":"2014-11-21T06:08:13-04:00","sunset":1416605514,"sunsetISO":"2014-11-21T17:31:54-04:00","snowDepthCM":null,"snowDepthIN":null,"precipMM":null,"precipIN":null,"solradWM2":null,"light":56,"sky":81},"raw":"TFFF 211330Z AUTO 07009KT 9999 SCT014 BKN021 BKN028 25\/24 Q1015"}]}